balinese_library
