Metadata-Version: 1.1
Name: balinese-library
Version: 0.0.4
Summary: A very basic balinese library about information extraction in balinese language
Home-page: UNKNOWN
Author: Ngurah Agus Sanjaya ER
Author-email: agus_sanjaya@unud.ac.id
License: MIT
Keywords: Information Extraction,Balinese
Platform: UNKNOWN
Classifier: Development Status :: 5 - Production/Stable
Classifier: Intended Audience :: Education
Classifier: Operating System :: Microsoft :: Windows :: Windows 10
Classifier: License :: OSI Approved :: MIT License
Classifier: Programming Language :: Python :: 3
